pathwaydb/__init__.py
pathwaydb/data/__init__.py
pathwaydb/data/go_term_names.json
pathwaydb/http/__init__.py
pathwaydb/http/cache.py
pathwaydb/http/client.py
pathwaydb/http/ratelimit.py
pathwaydb/mapper/__init__.py
pathwaydb/mapper/id_converter.py
pathwaydb/storage/__init__.py
pathwaydb/storage/annotation_db.py
pathwaydb/storage/go_db.py
pathwaydb/storage/kegg_db.py
pathwaydb/storage/msigdb_db.py
pathwaydb-0.2.0.dist-info/licenses/LICENSE
pathwaydb-0.2.0.dist-info/METADATA
pathwaydb-0.2.0.dist-info/WHEEL
pathwaydb-0.2.0.dist-info/top_level.txt
pathwaydb-0.2.0.dist-info/RECORD
